ore/__init__.py
ore/combinator.py
ore/error.py
ore/parser_state.py
ore/result.py
ore/run.py
ore/source.py
ore/source_position.py
ore/source_span.py
ore/combinators/__init__.py
ore/combinators/alt.py
ore/combinators/any_symbol.py
ore/combinators/one_of_symbols.py
ore/combinators/safe.py
ore/combinators/sequence.py
ore/combinators/string.py
ore/combinators/symbol.py
ore/combinators/take_n.py
ore/combinators/take_until.py
ore/combinators/take_while.py
ore/combinators/take_while_possible.py
ore/combinators/transform.py
ore_combinators/__init__.py
ore_combinators/combinator.py
ore_combinators/error.py
ore_combinators/parser_state.py
ore_combinators/result.py
ore_combinators/run.py
ore_combinators/source.py
ore_combinators/source_position.py
ore_combinators/source_span.py
ore_combinators/combinators/__init__.py
ore_combinators/combinators/alt.py
ore_combinators/combinators/any_symbol.py
ore_combinators/combinators/one_of_symbols.py
ore_combinators/combinators/safe.py
ore_combinators/combinators/sequence.py
ore_combinators/combinators/string.py
ore_combinators/combinators/symbol.py
ore_combinators/combinators/take_n.py
ore_combinators/combinators/take_until.py
ore_combinators/combinators/take_while.py
ore_combinators/combinators/take_while_possible.py
ore_combinators/combinators/transform.py
ore_combinators-0.0.5.dist-info/LICENSE
ore_combinators-0.0.5.dist-info/METADATA
ore_combinators-0.0.5.dist-info/WHEEL
ore_combinators-0.0.5.dist-info/top_level.txt
ore_combinators-0.0.5.dist-info/RECORD
