Metadata-Version: 2.1
Name: ore-combinators
Version: 0.0.5
Summary: Parser combinator library for Python
Home-page: UNKNOWN
Author: Igor Kraglik
Author-email: kraglik.i.d@gmail.com
License: MIT
Project-URL: homepage, https://github.com/kraglik/ore
Project-URL: repository, https://github.com/kraglik/ore
Keywords: parser combinator ore
Platform: UNKNOWN
Requires-Python: ==3.*,>=3.6.0
License-File: LICENSE
